SocketFactory/__init__.py
SocketFactory/alignment_main.py
SocketFactory/analysis_mesh_main.py
SocketFactory/decimation_main.py
SocketFactory/differential_pca_main.py
SocketFactory/geodesic_path_main.py
SocketFactory/landmark_main.py
SocketFactory/pca_main.py
SocketFactory/pts_file_generation_main.py
SocketFactory/quality_mapper_main.py
SocketFactory/registration_main.py
SocketFactory/roi_main.py
SocketFactory/slices_main.py
SocketFactory/alignment/__init__.py
SocketFactory/alignment/alignment_tf.py
SocketFactory/alignment/alignment_tt.py
SocketFactory/alignment/common.py
SocketFactory/gui_alignment/__init__.py
SocketFactory/gui_alignment/alignment_visualization_window.py
SocketFactory/gui_alignment/gui_alignment.py
SocketFactory/gui_decimation/__init__.py
SocketFactory/gui_decimation/mesh_decimation.py
SocketFactory/gui_landmark/__init__.py
SocketFactory/gui_landmark/landmark_selection.py
SocketFactory/gui_landmark/selection_windows.py
SocketFactory/gui_outcomes/__init__.py
SocketFactory/gui_outcomes/gui_compare_mesh.py
SocketFactory/gui_outcomes/gui_distance.py
SocketFactory/gui_outcomes/gui_geodesic_distance.py
SocketFactory/gui_outcomes/gui_roi_selection.py
SocketFactory/gui_outcomes/gui_slices.py
SocketFactory/gui_outcomes/outcome_visualization_window.py
SocketFactory/gui_pca/__init__.py
SocketFactory/gui_pca/pca_handling_window.py
SocketFactory/gui_pca/pca_main_window.py
SocketFactory/gui_registration/__init__.py
SocketFactory/gui_registration/mesh_visualization_window.py
SocketFactory/gui_registration/parameters_dialog.py
SocketFactory/gui_registration/register_other_meshes_window.py
SocketFactory/gui_registration/registration_main_window.py
SocketFactory/outcomes/__init__.py
SocketFactory/outcomes/distance.py
SocketFactory/outcomes/geodesic_path.py
SocketFactory/outcomes/region_of_interest.py
SocketFactory/outcomes/slices.py
SocketFactory/pca/__init__.py
SocketFactory/pca/pca.py
SocketFactory/registration/__init__.py
SocketFactory/registration/common.py
SocketFactory-1.0.7.dist-info/LICENSE
SocketFactory-1.0.7.dist-info/METADATA
SocketFactory-1.0.7.dist-info/WHEEL
SocketFactory-1.0.7.dist-info/top_level.txt
SocketFactory-1.0.7.dist-info/RECORD
