Metadata-Version: 2.1
Name: SocketFactory
Version: 1.0.7
Summary: Python library to analyze how the shape of the stump evolves, from the cast to the finished socket, based on the three-dimensional digitization of the surfaces.
Home-page: https://github.com/LindaGuiducci/SocketFactory.git
Author: Linda Guiducci and Ioana Madalina Raileanu
Author-email: ioanamadalina.raileanu@mail.polimi.it
License: UNKNOWN
Platform: UNKNOWN
Classifier: Programming Language :: Python :: 3.8
Classifier: License :: OSI Approved :: GNU General Public License v3 or later (GPLv3+)
Classifier: Operating System :: OS Independent
Classifier: Topic :: Scientific/Engineering
Requires-Python: >=3.8
Requires-Dist: vtk (==9.0.1)
Requires-Dist: PyQt5 (>=5.15)
Requires-Dist: numpy
Requires-Dist: scipy
Requires-Dist: scikit-learn
Requires-Dist: pandas
Requires-Dist: networkx
Requires-Dist: networkx-query
Requires-Dist: openpyxl
Requires-Dist: plyfile
Requires-Dist: pymeshlab
Requires-Dist: pyvista
